m3georeferencer/__init__.py
m3georeferencer/base_image.py
m3georeferencer/cli.py
m3georeferencer/custom_types.py
m3georeferencer/georeferencer.py
m3georeferencer/georeferencer_classes.py
m3georeferencer/py.typed
m3georeferencer/read_m3.py
m3georeferencer/target_image.py
m3georeferencer/utils.py
m3georeferencer-0.1.3.dist-info/entry_points.txt
m3georeferencer-0.1.3.dist-info/licenses/LICENSE
m3georeferencer-0.1.3.dist-info/METADATA
m3georeferencer-0.1.3.dist-info/WHEEL
m3georeferencer-0.1.3.dist-info/RECORD
