Metadata-Version: 2.4
Name: m3georeferencer
Version: 0.1.3
Summary: Georeferencing GUI built for Moon Mineralogy Mapper data
License: LICENSE
License-File: LICENSE
Author: Z.M. Vig
Author-email: zvig@umd.edu
Requires-Python: >=3.13
Classifier: License :: Other/Proprietary License
Classifier: Programming Language :: Python :: 3
Classifier: Programming Language :: Python :: 3.13
Classifier: Programming Language :: Python :: 3.14
Requires-Dist: PyQt6 (>6.9)
Requires-Dist: arguably (>=1.3.0)
Requires-Dist: matplotlib (>=3.10.6,<4.0.0)
Requires-Dist: numpy (>2.2)
Requires-Dist: rasterio (>=1.4.3,<2.0.0)
